{
  "users": [
    {
      "password": "1234",
      "id": 1
    },
    {
      "id": 2,
      "email": "parth.bhavsar@theonetechnologies.co.in",
      "password": "Test@1234",
      "dob": "1997-10-29",
      "isVerified": true
    },
    {
      "email": "test1@gmail.com",
      "password": "Test@1234",
      "dob": "21-12-2021",
      "isVerified": true,
      "id": 3
    },
    {
      "email": "mansi.senjaliya@estatic-infotech.com",
      "password": "Test@1234",
      "dob": "2022-05-05",
      "isVerified": true,
      "id": 4
    }
  ]
}